[
  {
    "homeTeam": "Washington Wizards",
    "visitorTeam": "Boston Celtics",
    "homePoints": 92,
    "visitorPoints": 108,
    "totalPoints": 200,
    "winningTeam": "visitor ML"
  },
  {
    "homeTeam": "Philadelphia 76ers",
    "visitorTeam": "Brooklyn Nets",
    "homePoints": 113,
    "visitorPoints": 98,
    "totalPoints": 211,
    "winningTeam": "home ML"
  },
  {
    "homeTeam": "New Orleans Pelicans",
    "visitorTeam": "Golden State Warriors",
    "homePoints": 108,
    "visitorPoints": 112,
    "totalPoints": 220,
    "winningTeam": "visitor ML"
  },
  {
    "homeTeam": "Chicago Bulls",
    "visitorTeam": "Atlanta Hawks",
    "homePoints": 136,
    "visitorPoints": 122,
    "totalPoints": 258,
    "winningTeam": "home ML"
  },
  {
    "homeTeam": "Portland Trail Blazers",
    "visitorTeam": "Houston Rockets",
    "homePoints": 88,
    "visitorPoints": 116,
    "totalPoints": 204,
    "winningTeam": "visitor ML"
  },
  {
    "homeTeam": "Milwaukee Bucks",
    "visitorTeam": "Indiana Pacers",
    "homePoints": 129,
    "visitorPoints": 117,
    "totalPoints": 246,
    "winningTeam": "home ML"
  },
  {
    "homeTeam": "Denver Nuggets",
    "visitorTeam": "Dallas Mavericks",
    "homePoints": 120,
    "visitorPoints": 123,
    "totalPoints": 243,
    "winningTeam": "visitor ML"
  },
  {
    "homeTeam": "Sacramento Kings",
    "visitorTeam": "Los Angeles Clippers",
    "homePoints": 104,
    "visitorPoints": 88,
    "totalPoints": 192,
    "winningTeam": "home ML"
  }
]
